{"type":"PR","pr":{"number":1,"head":"4093ec8b039603f41ef3990f045d3dd58b4766fc"},"user":"facundonahuelmuller","status":"pending_publish","branch":"cms/2023-04-16-hola","collection":"blog","title":"Hola","description":"No Description!","objects":{"entry":{"path":"/content/blog/2023-04-16-hola.md","sha":"db2f97a75caaa14ff61a5729f08e1c5660d76e76"},"files":[{"path":"/assets/images/manos.png","sha":"b6a0fd76a59a5e42a214f7883147bb01da4675ef"},{"path":"/assets/images/hola.jpg","sha":"db22b021a6658975684bb61a9fdfb3eb6ed66d70"}]},"timeStamp":"2023-04-16T18:25:43.447Z"}